Metadata-Version: 2.4
Name: vaani-speech-to-text
Version: 0.1.3
Summary: Vaani is an open-source, AI-powered speech-to-text desktop app. Vaani (वाणी) refers to "speech" or "voice" in Sanskrit.
Author-email: Nilesh Raghuvanshi <nilesh.raghuvanshi@gmail.com>
License-Expression: Apache-2.0
Project-URL: Homepage, https://github.com/webstruck/vaani-speech-to-text
Project-URL: Repository, https://github.com/webstruck/vaani-speech-to-text
Keywords: speech-to-text,whisper,ai,transcription,desktop,qt,pyside6,offline,privacy
Classifier: Development Status :: 4 - Beta
Classifier: Intended Audience :: Developers
Classifier: Intended Audience :: End Users/Desktop
Classifier: Operating System :: Microsoft :: Windows
Classifier: Operating System :: MacOS
Classifier: Operating System :: POSIX :: Linux
Classifier: Programming Language :: Python :: 3
Classifier: Programming Language :: Python :: 3.10
Classifier: Programming Language :: Python :: 3.11
Classifier: Programming Language :: Python :: 3.12
Classifier: Topic :: Multimedia :: Sound/Audio :: Speech
Classifier: Topic :: Scientific/Engineering :: Artificial Intelligence
Classifier: Topic :: Desktop Environment
Classifier: Environment :: Win32 (MS Windows)
Requires-Python: >=3.10
License-File: LICENSE
Requires-Dist: faster-whisper>=1.1.1
Requires-Dist: keyboard>=0.13.5
Requires-Dist: matplotlib>=3.10.1
Requires-Dist: noisereduce>=3.0.3
Requires-Dist: numpy>=2.2.4
Requires-Dist: ollama>=0.4.8
Requires-Dist: pyaudio>=0.2.14
Requires-Dist: pyautogui>=0.9.54
Requires-Dist: pyperclip>=1.9.0
Requires-Dist: pyside6>=6.9.0
Requires-Dist: pywin32>=310
Requires-Dist: scipy>=1.15.2
Dynamic: license-file
